mdstream/LICENSE
mdstream/README.md
mdstream/__about__.py
mdstream/__init__.py
mdstream/main.py
mdstream-0.3.4.dist-info/METADATA
mdstream-0.3.4.dist-info/WHEEL
mdstream-0.3.4.dist-info/entry_points.txt
mdstream-0.3.4.dist-info/licenses/LICENSE
mdstream-0.3.4.dist-info/RECORD
